pulumiverse_configcat/__init__.py
pulumiverse_configcat/_inputs.py
pulumiverse_configcat/_utilities.py
pulumiverse_configcat/configuration.py
pulumiverse_configcat/environment.py
pulumiverse_configcat/get_configurations.py
pulumiverse_configcat/get_environments.py
pulumiverse_configcat/get_organizations.py
pulumiverse_configcat/get_permission_groups.py
pulumiverse_configcat/get_products.py
pulumiverse_configcat/get_sdk_keys.py
pulumiverse_configcat/get_segments.py
pulumiverse_configcat/get_settings.py
pulumiverse_configcat/get_tags.py
pulumiverse_configcat/get_webhook_signing_keys.py
pulumiverse_configcat/integration.py
pulumiverse_configcat/outputs.py
pulumiverse_configcat/permission_group.py
pulumiverse_configcat/product.py
pulumiverse_configcat/product_preferences.py
pulumiverse_configcat/provider.py
pulumiverse_configcat/pulumi-plugin.json
pulumiverse_configcat/py.typed
pulumiverse_configcat/segment.py
pulumiverse_configcat/setting.py
pulumiverse_configcat/setting_tag.py
pulumiverse_configcat/setting_value.py
pulumiverse_configcat/setting_value_v2.py
pulumiverse_configcat/tag.py
pulumiverse_configcat/webhook.py
pulumiverse_configcat/config/__init__.py
pulumiverse_configcat/config/__init__.pyi
pulumiverse_configcat/config/vars.py
pulumiverse_configcat-5.0.0.dist-info/METADATA
pulumiverse_configcat-5.0.0.dist-info/WHEEL
pulumiverse_configcat-5.0.0.dist-info/top_level.txt
pulumiverse_configcat-5.0.0.dist-info/RECORD
